structure/models/__init__.py
structure/models/generate_models.py
structure/models/get_classes.py
structure/models/models.py
structure/parsing/__init__.py
structure/parsing/aggregation.py
structure/parsing/file_handlers.py
structure/parsing/parse.py
structure/parsing/utils/json_fixer.py
structure/server/server.py
structure_llm-0.1.0.dist-info/METADATA
structure_llm-0.1.0.dist-info/WHEEL
structure_llm-0.1.0.dist-info/RECORD
